[{"id": 3, "nome": "eu", "email": "eu@gmail.com", "fone": "1", "senha": "senha"}, {"id": 4, "nome": "teste", "email": "teste", "fone": "29", "senha": "senha"}, {"id": 1, "nome": "admin", "email": "admin", "fone": "admin", "senha": " "}, {"id": 5, "nome": "jpmlstador", "email": "jpoe", "fone": "65435", "senha": "noltib"}, {"id": 6, "nome": "isaque", "email": "negrizaki", "fone": " 579409", "senha": "senha"}, {"id": 7, "nome": "comunista", "email": "gustavo@gmail.com", "fone": "67692411", "senha": "SENHA"}]